odoo/addons/budget_plan_detail/README.rst
odoo/addons/budget_plan_detail/__init__.py
odoo/addons/budget_plan_detail/__manifest__.py
odoo/addons/budget_plan_detail/hooks.py
odoo/addons/budget_plan_detail/data/budget_constraint_data.xml
odoo/addons/budget_plan_detail/data/server_action.xml
odoo/addons/budget_plan_detail/models/__init__.py
odoo/addons/budget_plan_detail/models/account_analytic_dimension.py
odoo/addons/budget_plan_detail/models/account_analytic_tag.py
odoo/addons/budget_plan_detail/models/account_move_line.py
odoo/addons/budget_plan_detail/models/analytic_account.py
odoo/addons/budget_plan_detail/models/base_budget_move.py
odoo/addons/budget_plan_detail/models/budget_control.py
odoo/addons/budget_plan_detail/models/budget_move_adjustment.py
odoo/addons/budget_plan_detail/models/budget_period.py
odoo/addons/budget_plan_detail/models/budget_plan.py
odoo/addons/budget_plan_detail/models/budget_source_fund.py
odoo/addons/budget_plan_detail/models/budget_transfer_item.py
odoo/addons/budget_plan_detail/readme/CONTRIBUTORS.md
odoo/addons/budget_plan_detail/readme/DESCRIPTION.md
odoo/addons/budget_plan_detail/readme/USAGE.md
odoo/addons/budget_plan_detail/report/__init__.py
odoo/addons/budget_plan_detail/report/budget_common_monitoring.py
odoo/addons/budget_plan_detail/report/budget_monitor_report.py
odoo/addons/budget_plan_detail/report/budget_monitor_report_view.xml
odoo/addons/budget_plan_detail/report/budget_source_fund_report.py
odoo/addons/budget_plan_detail/report/budget_source_fund_report_view.xml
odoo/addons/budget_plan_detail/security/ir.model.access.csv
odoo/addons/budget_plan_detail/static/description/icon.png
odoo/addons/budget_plan_detail/static/description/index.html
odoo/addons/budget_plan_detail/tests/__init__.py
odoo/addons/budget_plan_detail/tests/common.py
odoo/addons/budget_plan_detail/tests/test_budget_plan_detail.py
odoo/addons/budget_plan_detail/views/account_budget_move.xml
odoo/addons/budget_plan_detail/views/account_move_view.xml
odoo_addon_budget_plan_detail-18.0.1.1.3.dist-info/METADATA
odoo_addon_budget_plan_detail-18.0.1.1.3.dist-info/WHEEL
odoo_addon_budget_plan_detail-18.0.1.1.3.dist-info/top_level.txt
odoo_addon_budget_plan_detail-18.0.1.1.3.dist-info/RECORD
